simple_sample/__init__.py
simple_sample/myClass.py
simple_sample/myClassAbstract.py
simple_sample/myClassInterface.py
tests/__init__.py
tests/testMyClass.py
tests/testMyClassAbstract.py
tests/testMyClassInterface.py
simple_sample-0.0.4.dist-info/LICENSE
simple_sample-0.0.4.dist-info/METADATA
simple_sample-0.0.4.dist-info/WHEEL
simple_sample-0.0.4.dist-info/top_level.txt
simple_sample-0.0.4.dist-info/RECORD
