Metadata-Version: 2.1
Name: simple-sample
Version: 0.0.4
Summary: A simple sample of a Python package prototype
Home-page: https://simple-sample.readthedocs.io/
Author: Alessandra Bilardi
Author-email: alessandra.bilardi@gmail.com
License: UNKNOWN
Project-URL: Source, https://github.com/bilardi/python-prototype
Project-URL: Bug Reports, https://github.com/bilardi/python-prototype/issues
Project-URL: Funding, https://donate.pypi.org
Platform: UNKNOWN
Classifier: Programming Language :: Python :: 3
Classifier: License :: OSI Approved :: MIT License
Classifier: Operating System :: OS Independent
Requires-Python: >=3.6
